{
  "connections": [
    {
      "source": {
        "port": "Reaction",
        "process": "Upstream"
      },
      "target": {
        "port": "Part1",
        "process": "Ligation"
      }
    },
    {
      "source": {
        "port": "Reaction",
        "process": "Downstream"
      },
      "target": {
        "port": "Part2",
        "process": "Ligation"
      }
    },
    {
      "source": {
        "port": "Reaction",
        "process": "Vector"
      },
      "target": {
        "port": "Vector",
        "process": "Ligation"
      }
    }
  ],
  "processes": {
    "Downstream": {
      "component": "RestrictionDigestion_conc"
    },
    "Ligation": {
      "component": "Ligation_2partsintovector"
    },
    "Upstream": {
      "component": "RestrictionDigestion_conc"
    },
    "Vector": {
      "component": "RestrictionDigestion_conc"
    }
  }
}